{
    "<page title>": "Avue Avg19wbv 2d 18.5 Led Cctv Monitor Black - Yikus.com",
    "aspectratio": ": 16:9",
    "brand": ": AVUE",
    "category": ": SURVEILANCE SYSTEMS",
    "color": ": Black",
    "ean": ": 0855597003664",
    "feature": [
        ": Multi-Language OSD And Built-In Speakers",
        ": VGA & BNC Inputs (VGA Cable Included)",
        ": 1360 X 768 Resolution (SXGA) Panels",
        ": 18.5 Inch High Resolution LED Monitor (over 420 TVL)",
        ": CE, FCC, CB, RoHS"
    ],
    "group": ": Photography",
    "label": ": AVUE",
    "manufacturer": ": AVUE",
    "model": ": AVG19WBV-2D",
    "mpn": ": AVG19WBV-2D",
    "order": ": Electronics",
    "part number": ": AVG19WBV-2D",
    "publisher": ": AVUE",
    "quantity": ": 1",
    "reports": [
        ": 1360 x 768 Resolution (SXGA) panels",
        ": VGA & BNC Inputs (VGA Cable included)",
        ": 18.5 inch High Resolution LED Monitor (over 420 TVL)",
        ": Multi-Language OSD and Built-In Speakers"
    ],
    "size": ": 22.2in L X 20.5in W X 18.6in H",
    "studio": ": AVUE",
    "title": ": AVUE AVG19WBV-2D 18.5\u2033 LED CCTV Monitor (Black)",
    "total items": ": 1",
    "upc": ": 855597003664"
}