{
    "<page title>": "Eizo Flexscan Ev2416wfs Bk Led Monitor 24 1920 X 1200 Tn 250  - Yikus.com",
    "aspectratio": ": 16:10",
    "brand": ": Eizo",
    "category": ": MONITOR",
    "ean": ": 0690592036930",
    "feature": [
        ": Product Line: FlexScan| Product Name: 24 FlexScan EV2416W WideScreen LED| Marketing Information: Slim Bezels Give The EV2416W An Attractive New Design, But Youll Be Even More Impressed By Its Visual E",
        ": Number Of Screens: 1| Screen Size: 24| Screen Mode: WUXGA| Response Time: 5 Ms| Aspect Ratio: 1610| Horizontal Viewing Angle: 170\u00b0| Vertical Viewing Angle: 160\u00b0| Adjustable Display Angle: Yes| Adjus",
        ": Marketing Information: A New Thin Bezel Design Saves Space On The Desktop And Minimizes Eye Movement Between Screens In A Multi-monitor Environment.| Marketing Information: Adjustable Stand| Marketing",
        ": Brightness: 250 Nit| Number Of Speakers: 2| Speakers: Yes| DVI: Yes| USB: Yes| USB Standard: USB 2.0| VGA: Yes| DisplayPort: Yes| Built-in Devices: USB Hub| Operating Power Consumption: 45 W| Standby"
    ],
    "group": ": PC Accessory",
    "item": [
        ": Marketing Information: A new thin bezel design saves space on the desktop and mi",
        ": Brightness: 250 Nit| Number of Speakers: 2| Speakers: Yes| DVI: Yes| USB: Yes| U",
        ": Product Line: FlexScan| Product Name: 24 FlexScan EV2416W WideScreen LED| Market",
        ": Number of Screens: 1| Screen Size: 24| Screen Mode: WUXGA| Response Time: 5 ms|"
    ],
    "label": ": EIZO",
    "manufacturer": ": EIZO",
    "model": ": EV2416WFS-BK",
    "mpn": ": EV2416WFS-BK",
    "order": ": Personal Computers",
    "part number": ": EV2416WFS-BK",
    "publisher": ": EIZO",
    "quantity": ": 1",
    "size": ": 24in L X 6.5in W X 18in H",
    "studio": ": EIZO",
    "title": ": EIZO FlexScan EV2416WFS-BK \u2013 LED Monitor \u2013 24\u2033 \u2013 1920 X 1200 \u2013 TN \u2013 250 Cd/m2 \u2013 1000:1 \u2013 5 Ms \u2013 DVI-D, VGA, DisplayPort \u2013 Speakers \u2013 Black",
    "upc": ": 690592036930"
}