{
    "<page title>": "ACER UM.HG6AA.D03 - Vology",
    "aspect ratio": "Widescreen - 16:9",
    "brightness": "300 cd/m2",
    "color": "Black",
    "color support": "16.7 million colors",
    "compliant standards": "MPR II",
    "contrast ratio": "100000000:1 (dynamic)",
    "device type": "LED-backlit LCD monitor - 27\"",
    "dimensions wxdxh": "25.2 in x 7 in x 17.4 in - with stand",
    "display position adjustments": "Tilt",
    "input connectors": "DVI, VGA",
    "manufacturer warranty": "3 years warranty",
    "native resolution": "FullHD 1920 x 1080 at 60 Hz",
    "product description": "Acer G276HL Dbd - LED monitor - 27\"",
    "response time": "6 ms",
    "weight": "10.1 lbs"
}