{
    "<page title>": "SAMSUNG S19A200NW - Vology",
    "aspect ratio": [
        "Widescreen - 16:10",
        "Widescreen - 16:10"
    ],
    "backlight technology": "LED backlight",
    "brightness": [
        "250 cd/m2",
        "250 cd/m2"
    ],
    "cables included": "1 x VGA cable",
    "color": [
        "Matte black",
        "Matte black"
    ],
    "compatible with windows 7": "\"Compatible with Windows 7\" software and devices carry Microsoft\u2019s assurance that these products have passed tests for compatibility and reliability with 32-bit and 64-bit Windows 7.",
    "connectivity": "Interfaces VGA",
    "contrast ratio": [
        "1000:1",
        "1000:1"
    ],
    "device type": "LED-backlit LCD monitor - 19\"",
    "diagonal size": "19\"",
    "dimensions  weight": "Dimensions & Weight Details With stand - width: 17.4 in - depth: 7.9 in - height: 15.5 in - weight: 6.8 lbs \u00a6 Without stand - width: 17.4 in - depth: 1.9 in - height: 11.8 in",
    "dimensions  weight details": "With stand - width: 17.4 in - depth: 7.9 in - height: 15.5 in - weight: 6.8 lbs \u00a6 Without stand - width: 17.4 in - depth: 1.9 in - height: 11.8 in",
    "dimensions wxdxh": [
        "17.4 in x 7.9 in x 15.5 in - with stand",
        "17.4 in x 7.9 in x 15.5 in - with stand"
    ],
    "display position adjustments": [
        "Tilt",
        "Tilt"
    ],
    "display type": "LED-backlit LCD monitor / TFT active matrix",
    "energy star qualified": "Yes",
    "environmental standards": [
        "EPEAT Compliant EPEAT Gold\nENERGY STAR Qualified Yes",
        "ENERGY STAR Qualified , EPEAT Gold"
    ],
    "epeat compliant": "EPEAT Gold",
    "features": "Power off timer, MagicColor, carrying handle, MagicAngle, MagicBright 3, Mega Dynamic Contrast Ratio",
    "flat panel mount interface": "100 x 100 mm",
    "general": "Weight 6.8 lbs\nBrightness 250 cd/m2\nAspect Ratio Widescreen - 16:10\nFeatures Power off timer, MagicColor, carrying handle, MagicAngle, MagicBright 3, Mega Dynamic Contrast Ratio\nResponse Time 5 ms\nDimensions (WxDxH) 17.4 in x 7.9 in x 15.5 in - with stand\nDisplay Type LED-backlit LCD monitor / TFT active matrix\nHorizontal Viewing Angle 170\nContrast Ratio 1000:1\nPanel Type TN\nBacklight Technology LED backlight\nVertical Viewing Angle 160\nDiagonal Size 19\"\nNative Resolution 1440 x 900\nColor Matte black",
    "horizontal viewing angle": "170",
    "input connectors": "VGA",
    "interfaces": "VGA",
    "mainspecs": "Microsoft Certification Compatible with Windows 7\nColor Matte black\nAspect Ratio Widescreen - 16:10\nResponse Time 5 ms\nEnvironmental Standards ENERGY STAR Qualified , EPEAT Gold\nProduct Description Samsung S19A200NW - LED monitor - 19\"\nManufacturer Warranty 3 years warranty\nContrast Ratio 1000:1\nBrightness 250 cd/m2\nPanel Type TN\nDisplay Position Adjustments Tilt\nInput Connectors VGA\nWeight 6.8 lbs\nDimensions (WxDxH) 17.4 in x 7.9 in x 15.5 in - with stand\nNative Resolution 1440 x 900\nDevice Type LED-backlit LCD monitor - 19\"",
    "manufacturer warranty": [
        "Service & Support Details Limited warranty - parts and labor - 3 years\nService & Support 3 years warranty",
        "3 years warranty"
    ],
    "mechanical": "Flat Panel Mount Interface 100 x 100 mm\nDisplay Position Adjustments Tilt",
    "microsoft certification": "Compatible with Windows 7",
    "miscellaneous": "Compatible with Windows 7 \"Compatible with Windows 7\" software and devices carry Microsoft\u2019s assurance that these products have passed tests for compatibility and reliability with 32-bit and 64-bit Windows 7.\nCables Included 1 x VGA cable",
    "native resolution": [
        "1440 x 900",
        "1440 x 900"
    ],
    "panel type": [
        "TN",
        "TN"
    ],
    "power": "Power Supply External\nVoltage Required AC 120/230 V ( 50/60 Hz )\nPower Consumption Stand by / Sleep 0.3 Watt\nPower Consumption Operational 20 Watt",
    "power consumption operational": "20 Watt",
    "power consumption stand by  sleep": "0.3 Watt",
    "power supply": "External",
    "product description": "Samsung S19A200NW - LED monitor - 19\"",
    "response time": [
        "5 ms",
        "5 ms"
    ],
    "service  support": "3 years warranty",
    "service  support details": "Limited warranty - parts and labor - 3 years",
    "vertical viewing angle": "160",
    "voltage required": "AC 120/230 V ( 50/60 Hz )",
    "weight": [
        "6.8 lbs",
        "6.8 lbs"
    ]
}