{
    "<page title>": "Buy HP Smart Buy 22\" E221 Full HD LED-LCD Monitor, Black Monitors - LED-LCD C9V76A8#ABA today at PC Connection",
    "attributes": "Height Adjustable",
    "brightness nitscdm2": "250 nit(s)",
    "color": "Black",
    "compatibility notes": "Bring your content to life with Full-HD resolution. Get vibrant text and graphics from the LED backlit panel, which also makes the monitor thin, light, and easy to position on a desk.\nFind your most comfortable working position so you can power through your day. Customizable tilt, height adjustment, swivel, and pivot settings\u2014the most adjustability available on an HP business display\u2014help you find your sweet spot.\nReduce power consumption and help lower your costs with an intelligent, energy efficient design featuring ENERGY STAR, EPEAT Gold, and TCO certifications.",
    "compliant standards": "Energy Star",
    "connector": [
        "Power",
        "HDDB15",
        "DisplayPort",
        "DVI-D"
    ],
    "connector type": [
        "DisplayPort",
        "DVI-D",
        "VGA",
        "Power"
    ],
    "contents": "Monitor, VGA cable, DisplayPort cable, USB cable, power cable, documentation",
    "contrast ratio": "1000:1",
    "digital video standard": "Digital Visual Interface (DVI)",
    "display position adjustments": [
        "Pivot (rotation)",
        "Swivel",
        "Tilt",
        "Height"
    ],
    "display size": "21.5 in",
    "display technology": [
        "LCD",
        "LED-backlit"
    ],
    "display type": "Widescreen",
    "dot pitch": "0.248 mm",
    "energy star qualified": "Yes",
    "image brightness": "250 cd/m2",
    "internal resolution max": "1920 x 1080",
    "portsconnectors": "(1) HDDB15 VGA\n(1) DVI-D\n(1) DisplayPort\n(1) Power in",
    "power notes": "Consumption: 36W (typ.)",
    "response timerate": "5 ms",
    "returns policy": "This product is subject to our return policy. Please see our complete return policy for details.",
    "viewing angle hv degrees": "170/160",
    "warranty  labor": "3 Years",
    "warranty  parts": "3 Years"
}