{
    "<page title>": "Buy 3M Privacy Filter for 27\" Widescreen LCD Display Glare Filters & Privacy Screens PF27.0W today at PC Connection",
    "compatibility notes": "Fits widescreen desktop monitors with a diagonally measured 27\" viewing screen",
    "contents": "Filter, documentation",
    "physical dimensions": "14.3\"h x 22.9\"w",
    "product type": "Display privacy filter",
    "returns policy": "This product is subject to our return policy. Please see our complete return policy for details.",
    "warranty  labor": "1 Year",
    "warranty  parts": "1 Year"
}