{
    "<page title>": "Buy Acer 23\" V236HL Cbmd Full HD LED-LCD Monitor, Black Monitors - LED-LCD UM.VV6AA.C02 today at PC Connection",
    "attributes": [
        "Dual speakers",
        "Speakers Included"
    ],
    "brightness nitscdm2": "250 nit(s)",
    "color": "Black",
    "color support": "16.7 million colors",
    "compatibility notes": "Dimensions with stand: 16.1\"h x 21.4\"w x 8.2\"d",
    "compliant standards": "TCO Displays 6.0",
    "connector": [
        "DVI",
        "HDDB15",
        "Power"
    ],
    "connector type": [
        "Power",
        "VGA",
        "DVI"
    ],
    "contents": "monitor, DVI cable, VGA cable, power cord, documentation",
    "contrast ratio": "100,000,000:1",
    "digital video standard": "Digital Visual Interface (DVI)",
    "display position adjustments": "Tilt",
    "display size": "23 in",
    "display technology": [
        "LCD",
        "LED-backlit"
    ],
    "display type": "Widescreen",
    "image brightness": "250 cd/m2",
    "internal resolution max": "1920 x 1080",
    "physical dimensions": "12.8\"h x 21.4\"w x 2\"d",
    "portsconnectors": "(1) DVI\n(1) HDDB15 VGA\n(1) Power in",
    "power notes": "Supply: 110-220VAC",
    "response timerate": "5 ms",
    "viewing angle hv degrees": "170/160",
    "warranty  labor": "3 Years",
    "warranty  parts": "3 Years"
}