{
    "<page title>": "47WX50MF-B, LG47WX50MF, LG Electronics, LCD Monitor, Kingsfield Computer Products Ltd",
    "aspect ratio": "16:9",
    "backlight technology": "LED",
    "brand name": "LG",
    "brightness": "2000 cd/m\u00b2",
    "displayport": "Yes",
    "dvi": "Yes",
    "features": [
        "TileMatrix (15x15)",
        "Ambient Light Sensor",
        "Temperature Sensor"
    ],
    "hdcp supported": "Yes",
    "hdmi": "Yes",
    "horizontal viewing angle": "178\u00b0",
    "manufacturer": "LG Electronics",
    "manufacturer part number": "47WX50MF-B",
    "maximum resolution": "1920 x 1080",
    "network rj45": "Yes",
    "number of screens": "1",
    "package type": "Retail",
    "panel technology": "In-plane Switching (IPS) Technology",
    "product model": "47WX50MF-B",
    "product name": "47WX50MF-B Widescreen LCD Monitor",
    "product type": "LCD Monitor",
    "screen mode": "Full HD",
    "screen size": "119.4 cm (47\")",
    "speakers": "No",
    "vertical viewing angle": "178\u00b0",
    "vga": "Yes"
}