{
    "<page title>": "VX2880ML, B921661, ViewSonic, LCD Monitor, Kingsfield Computer Products Ltd",
    "adjustable display angle": "Yes",
    "backlight technology": "LED",
    "brand name": "Viewsonic",
    "brightness": "300 cd/m\u00b2",
    "colour": "Black",
    "colour support": "1.07 Billion Colors",
    "contrast ratio": "50,000,000:1",
    "depth": "52 mm",
    "depth with stand": "240 mm",
    "displayport": "Yes",
    "dvi": "Yes",
    "features": [
        "Flicker-free",
        "Mobile High-Definition Link (MHL)"
    ],
    "hdmi": "Yes",
    "height": "412.5 mm",
    "height with stand": "510.58 mm",
    "horizontal viewing angle": "170\u00b0",
    "manufacturer": "Viewsonic Corporation",
    "manufacturer part number": "VX2880ML",
    "maximum resolution": "3840 x 2160",
    "mount type": "Wall Mountable",
    "number of screens": "1",
    "number of speakers": "2",
    "panel technology": "Twisted Nematic Film (TN Film)",
    "platform supported": "PC",
    "product model": "VX2880ml",
    "product name": "VX2880ml Widescreen LCD Monitor",
    "product series": "VX",
    "product type": "LCD Monitor",
    "response time": "5 ms",
    "screen mode": "QFHD",
    "screen size": "71.1 cm (28\")",
    "screen surface": "Anti-glare",
    "speakers": "Yes",
    "tilt angle": "-5\u00b0to20\u00b0",
    "vertical viewing angle": "160\u00b0",
    "vesa mount compatible": "Yes",
    "vesa mount standard": "100 x 100",
    "width": "660 mm",
    "width with stand": "659.96 mm"
}