{
    "<page title>": "HP EliteDisplay E190i - MBE",
    "aspect ratio": "5:4",
    "builtin camera": [
        "No",
        "No",
        "No"
    ],
    "builtin speakers": [
        "No",
        "No",
        "No"
    ],
    "cable lock slot": [
        "Kensington",
        "Kensington"
    ],
    "colour of product": [
        "Silver",
        "Silver"
    ],
    "contrast ratio dynamic": "3000000:1",
    "contrast ratio typical": "1000:1",
    "depth": "4.7 cm",
    "depth with stand": "19.2 cm",
    "display": "LCD",
    "display brightness": "250 cd/m\u00c2\u00b2",
    "display diagonal": "48.01 cm (18.9\")",
    "display diagonal metric": "48 cm",
    "display resolution": "1280 x 1024 pixels",
    "display technology": "IPS",
    "displayports quantity": "1",
    "dvi port": "Yes",
    "dvid ports quantity": "1",
    "energy efficiency class": "Unspecified",
    "energy star certified": "Yes",
    "epeat compliance": "Gold",
    "height": "34.7 cm",
    "height adjustment": "Yes",
    "height with stand": "48.6 cm",
    "input frequency": "50/60 Hz",
    "input voltage": "100 - 240V",
    "pixel pitch": "0.2928 x 0.2928 mm",
    "power consumption standby": "0.5W",
    "power consumption typical": "25W",
    "response time": "8 ms",
    "swivel angle range": "-180 - 180\u00c2\u00b0",
    "swivelling": "Yes",
    "thin client installed": "No",
    "tilt adjustment": "Yes",
    "tilt angle": "-5 - 25\u00c2\u00b0",
    "tv tuner integrated": [
        "No",
        "No"
    ],
    "usb 20 ports quantity": "3",
    "vga dsub ports quantity": "1",
    "viewing angle horizontal": "178\u00c2\u00b0",
    "viewing angle vertical": "178\u00c2\u00b0",
    "weight": "4.9 kg",
    "width": "41.7 cm",
    "width with stand": "41.7 cm"
}