{
    "<page title>": "OHC24 Shop : Monitor > Monitor search help > Samsung - T28C570EW LT28C570EW/EN",
    "aspect ratio": "Widescreen",
    "brightness": "300 cd/m2",
    "colour": "Gloss black",
    "compliant standards": "DDC-2B, ISO 9241-307",
    "contrast ratio": "3000:1",
    "device type": "LED-backlit LCD monitor - 28\"",
    "digital tv tuner": "DVB-C, DVB-T",
    "dimensions wxdxh": "66.1 cm x 20 cm x 48.51 cm - with stand",
    "display position adjustments": "Tilt",
    "energy class": "Class A",
    "energy consumption per year": "45.3 kWh",
    "environmental standards": "ENERGY STAR Qualified",
    "input connectors": "2xHDMI, VGA , composite video, component video",
    "manufacturer warranty": "2 years warranty",
    "native resolution": "FullHD 1920 x 1080",
    "product description": "Samsung T28C570EW - LED monitor - 28\"",
    "response time": "2 ms (gray-to-gray)",
    "weight": "5.5 kg"
}