{
    "<page title>": "Purchase the MDT551S, Mitsubishi LCD Screen, Mitsubishi 55 inches WS LCD, 1300:1 1080P HDMI DVI-D 10MS NARROW BEZEL",
    "analogue video input signals": "PAL, SECAM, NTSC4.43, PAL60",
    "backlight life": "50,000 hour(s)",
    "brightness": "700 cd/m2",
    "cables included": "VGA cable",
    "colour depth": "Up to 1.06 billion colours",
    "compatible with windows 7": "\"Compatible with Windows 7\" software and devices carry Microsoft\u00c2\u0092s assurance that these products have passed tests for compatibility and reliability with 32-bit and 64-bit Windows 7.",
    "compliant standards": "Plug and Play, FCC Class A certified, C-Tick, BSMI, cUL, DDC-2B, AS/NZS 60950-1, DOC, DDC/CI, RoHS, UL 60950-1, GOST-R",
    "connector type": "1 x VGA input ( 15 PIN HD D-Sub (HD-15) ) \u00c2\u00a6 1 x DVI-D input ( 24 PIN Digital DVI ) \u00c2\u00a6 1 x component video / RGB input ( BNC x 5 ) \u00c2\u00a6 1 x HDMI input ( 19 pin HDMI Type A ) \u00c2\u00a6 1 x DisplayPort input ( 20 pin DisplayPort ) \u00c2\u00a6 1 x composite video input/output ( BNC ) \u00c2\u00a6 1 x S-Video input / output ( 4 PIN mini-DIN ) \u00c2\u00a6 2 x audio line-in ( RCA phono x 2 ) \u00c2\u00a6 1 x audio input ( mini-phone stereo 3.5 mm ) \u00c2\u00a6 1 x remote control input ( 9 PIN D-Sub ) \u00c2\u00a6 1 x network ( RJ-45 ) \u00c2\u00a6 1 x VGA output ( 15 PIN HD D-Sub (HD-15) ) \u00c2\u00a6 1 x audio line-out ( RCA phono x 2 ) \u00c2\u00a6 1 x speakers output ( terminal block (clamp) ) \u00c2\u00a6 1 x remote control output ( 9 PIN D-Sub ) \u00c2\u00a6 1 x USB upstream ( 4 PIN USB Type B ) \u00c2\u00a6 4 x USB downstream ( 4 PIN USB Type A )",
    "depth": "12.7 cm",
    "depth shipping": "34.6 cm",
    "description technical detail": "Mitsubishi LCD MDT551S 55 inch Wide Screen Display TV\nMitsubishi LCD MDT551S 55 Inch Wide Screen Monitor is perfect for communication boards, classroom staging, and retail shops.\nProduct Overview\nThe Mitsubishi LCD MDT551S Display 55 Inch Monitor answers your requirements for digital signage, communication board, retail shops, and broadcast displays to improve your facilities through all form publicity to reception messages to very important up to date news and information.This is completing versatile with high quality technologies that make it more reliable and efficient LCD panel with input range from DisplayPort, Sub 15, DVI-D and HDMI. The Mitsubishi LCD MDT551S Display Cheap Screen Panel also features both frontage and back ambient light sensors for the eventual in fixing flexibility. The high quality LCD monitor automatically regulates its brightness based on the ambient light makes sure your information is always apparent and lively. All these features help to improved protection against image preservation and image resolution.\nKey Features\nIndustrial Grade LCD Panel\nComplete High Definition Resolution\nWide Screening Angle\nEnsure High Quality Colour with Contrast Ratio 1300:1\nBuilt In Speaker (10W)\nTiling Capability Up to 25 Panel\nMultiple Input & Output Connector\nHeat Status Observance\nCat5 Transmitter and Receiver\nOPS (Open Pluggable Specification)",
    "diagonal size": [
        "55\" Class ( 54.6\" viewable )",
        "55\" Class ( 54.6\" viewable )"
    ],
    "diagonal size cm": [
        "140 cm ( 138.8 cm viewable )",
        "140 cm ( 138.8 cm viewable )"
    ],
    "dimensions": "Without stand",
    "dimensions wxdxh": "125 cm x 12.7 cm x 72.1 cm - without stand",
    "display format": [
        "1080p (FullHD)",
        "1080p (FullHD)"
    ],
    "energy star qualified": "Yes",
    "environmental standards": "ENERGY STAR Qualified",
    "expansion slots": "1 x OPS slot",
    "external speakers amplifier power total": "14 Watt",
    "features": [
        "Closed caption, USB Hub",
        "Black Level Expander, Vertical Compression, ambient light sensor (ALS), screen saver, picture on picture (no tuner), black level correction, picture side picture (no tuner), picture in picture (no tuner), portrait mode, landscape mode, Video Wall",
        "Black Level Expander, Vertical Compression, ambient light sensor (ALS), screen saver, picture on picture (no tuner), black level correction, picture side picture (no tuner), picture in picture (no tuner), portrait mode, landscape mode, Video Wall"
    ],
    "flat panel mount interface": "200 x 200 mm",
    "hdcp compatible": [
        "Yes",
        "Yes"
    ],
    "hdmi ports qty": [
        "1 port(s)",
        "1 port(s)"
    ],
    "height": "72.1 cm",
    "height shipping": "93.8 cm",
    "humidity range operating": "20 - 80%",
    "image aspect ratio": [
        "16:9",
        "16:9"
    ],
    "image contrast ratio": "1300:1",
    "input video formats": [
        "480p, 720p, 1080i, 1080p, 480i, 576i, 576p",
        "480p, 720p, 1080i, 1080p, 480i, 576i, 576p"
    ],
    "lcd display technology": "IPS",
    "manufacturer": "Mitsubishi",
    "manufacturer part ": "MDT551S",
    "manufacturer warranty": "3 years warranty",
    "max hsync rate": "91.1 kHz",
    "max operating temperature": "40 \u00c2\u00b0C",
    "max vsync rate": "85 Hz",
    "microsoft certification": "Compatible with Windows 7",
    "min operating temperature": "5 \u00c2\u00b0C",
    "nominal voltage": "AC 120/230 V ( 50/60 Hz )",
    "output power  total": "20 Watt",
    "pc interface": [
        "DVI, VGA (HD-15), HDMI, DisplayPort",
        "DVI, VGA (HD-15), HDMI, DisplayPort"
    ],
    "pixel pitch": "0.63 x 0.63mm",
    "power": "AC 120/230 V ( 50/60 Hz )",
    "power consumption operational": [
        "316 Watt",
        "316 Watt"
    ],
    "power consumption stand by  sleep": "1 Watt",
    "product description": "Mitsubishi MDT551S - 55\" Class ( 54.6\" viewable ) LCD flat panel display",
    "product type": [
        "LCD flat panel display",
        "LCD flat panel display"
    ],
    "remote control": "Remote control",
    "resolution": [
        "1920 x 1080",
        "1920 x 1080"
    ],
    "response time": "10 ms",
    "service  support": "3 years warranty",
    "service  support details": "Limited warranty - parts and labour - 3 years \u00c2\u00a6 Limited warranty - replacement - 3 years \u00c2\u00a6 Technical support - 3 years",
    "sound output mode": [
        "Stereo",
        "Stereo"
    ],
    "speaker system": [
        "2 speakers",
        "2 speakers"
    ],
    "speakers": "2 x main channel speaker - built-in - 10 Watt",
    "stand": "Optional",
    "supported computer resolutions": "1920 x 1200 (WUXGA), 1024 x 768 (XGA), 640 x 480 (VGA), 800 x 600 (SVGA), 1280 x 768 (WXGA), 1280 x 1024 (SXGA), 1600 x 1200 (UXGA), 1360 x 768, 1920 x 1080",
    "targeting": [
        "Commercial use",
        "Commercial usage",
        "Commercial use"
    ],
    "technology": "IPS",
    "tv tuner": [
        "No tuner",
        "No tuner"
    ],
    "type": "Remote control",
    "video interface": [
        "Component, composite, HDMI, S-Video",
        "Component, composite, HDMI, S-Video"
    ],
    "viewing angle": "178 degrees",
    "viewing angle vertical": "178 degrees",
    "weight": [
        "37 kg",
        "37 kg"
    ],
    "weight shipping": "47.5 kg",
    "width": "125 cm",
    "width shipping": "147.4 cm"
}