{
    "<page title>": "NEC E232WMT-BK 60Hz 23.0\" Monitor (E232WMT-BK) - PCPartPicker Canada",
    "aspect ratio": "16:9",
    "brightness": "250 cd/m\u00b2",
    "builtin speakers": "Yes",
    "contrast ratio": "DC 15,000:1 (1000:1)",
    "display colors": "16700000",
    "dvi": "1",
    "hdmi": "1",
    "ips": "Yes",
    "led": "Yes",
    "manufacturer": "NEC",
    "part": "E232WMT-BK",
    "recommended resolution": "1920 x 1080",
    "refresh rate": "60Hz",
    "response time": "5 ms",
    "screen size": "23\"",
    "vga": "1",
    "viewing angle": "170\u00b0 H x 170\u00b0 V",
    "widescreen": "Yes"
}