{
    "<page title>": "ACER LED 19 B196Lwmdr MONITOR LED",
    "ac power in": "Si",
    "classe efficienza energetica": "Non specificato",
    "colore del prodotto": "Nero",
    "compatibilit\u00e0 3d": "N",
    "dimensioni schermo": "482.6 mm (19 \")",
    "fotocamera integrata": "N",
    "indicatore led alimentazione": "Si",
    "led standby": "Si",
    "luminosit\u00e0 schermo": "250 cd/m\u00b2",
    "rapporto di contrasto dinamico": "100000000:1",
    "sintonizzatore tv integrato": "N",
    "source datasheet": ".",
    "tempo di risposta": "5 ms",
    "thin client installato": "N",
    "tipologia display": "LCD"
}