{
    "<page title>": "Samsung SyncMaster S22A450BW Widescreen LCD Monitor Matte Black 729507816869 | eBay",
    "aspect ratio": "16:10",
    "brightness": "250 cd/m\u00c2\u00b2",
    "condition": "Used: An item that has been used previously. The item may have some signs of cosmetic wear, but is fully\noperational and functions as intended. This item may be a floor model or store return that has been used. See the seller\u00e2\u0080\u0099s listing for full details and description of any imperfections.\nSee all condition definitions- opens in a new window or tab\n... Read moreabout the condition\nBrand:\nSamsung",
    "contrast ratio": "1000:1",
    "display technology": "LCD",
    "max. resolution": "1680 x 1050",
    "model": "S22A450BW",
    "mpn": "LS22A450BWT/XK",
    "response time": "5 ms",
    "screen size": "22\"",
    "upc": "729507817286",
    "video inputs": "DVI, VGA D-Sub"
}