{
    "<page title>": "New Samsung SyncMaster S22A200B 22\" Widescreen LED Backlitlcd Monitor 729507816845 | eBay",
    "aspect ratio": "16:9",
    "brightness": "250 cd/m\u00c2\u00b2",
    "colors supported": "Not specified by manufacturer",
    "condition": "New: A brand-new, unused, unopened, undamaged item in its original packaging (where packaging is\napplicable). Packaging should be the same as what is found in a retail store, unless the item is handmade or was packaged by the manufacturer in non-retail packaging, such as an unprinted box or plastic bag. See the seller's listing for full details.\nSee all condition definitions- opens in a new window or tab\n... Read moreabout the condition\nBrand:\nSamsung",
    "contrast ratio": "1000:1",
    "display technology": "LED LCD",
    "max. resolution": "1920 x 1080",
    "model": "S22A200B",
    "response time": "5 ms",
    "screen size": "22\"",
    "system": "Desktop",
    "type": "LED",
    "upc": "729507816845",
    "video inputs": "DVI-D",
    "viewable size": "21.5\"",
    "viewing angle": "170\u00c2\u00b0/160\u00c2\u00b0"
}