{
    "<page title>": "Asus VS24AH P 24 1\" LED LCD Monitor 16 10 5 MS 886227438099 | eBay",
    "adjustable display angle": "Yes",
    "aspect ratio": "16:10",
    "backlight technology": "LED",
    "brand name": "Asus",
    "certifications  standards": "CE BSMI CB C-Tick FCC PSE UL/cUL VCCI WHQL",
    "color": "Black",
    "color supported": "16.7 Million Colors",
    "condition": "New: A brand-new, unused, unopened, undamaged item in its original packaging (where packaging is\napplicable). Packaging should be the same as what is found in a retail store, unless the item is handmade or was packaged by the manufacturer in non-retail packaging, such as an unprinted box or plastic bag. See the seller's listing for full details.\nSee all condition definitions- opens in a new window or tab\n... Read moreabout the condition\nBrand:\nASUS",
    "contrast ratio": "80,000,000:1",
    "depth with stand": "8.09\"",
    "dvi": "Yes",
    "features": "Security Lock\nSplendid Video Intelligence Technology",
    "general information": "Marketing Information 178\u00c2\u00b0 of Vertical and Horizontal Ultra Wide View Delicate touches make a monitor truly great, VS24AH-P 1920x1200 IPS LED monitor, with16:10 aspect ratio, 80,000,000:1 high contrast ratio and HDMI interface, is optimized for the finest image and color quality. This approach extends to the sturdy stand and slim profile without compromising style in ensuring stability and durability.",
    "green compliance certificateauthority": "ENERGY STAR\nErP\nRoHS\nEPEAT Gold\nJ-Moss (Japanese RoHS)\nTCO Certified Displays 6.0\nWEEE",
    "hdcp supported": "Yes",
    "hdmi": "Yes",
    "headphone": "Yes",
    "horizontal viewing angle": "178\u00c2\u00b0",
    "interfacesports": "VGA Yes",
    "manufacturer": "ASUS Computer International",
    "manufacturer part number": "VS24AH-P",
    "max resolution": "1920 x 1200",
    "maximum resolution": "1920 x 1200",
    "miscellaneous": "Green Compliant Yes",
    "model": "VS24AH-P",
    "mount type": "Wall Mountable",
    "number of screens": "1",
    "offmode power consumption": "500 mW",
    "panel technology": "In-plane Switching (IPS) Technology",
    "physical characteristics": "Height with Stand 17.36\"",
    "platform supported": "PC",
    "power description": "Operating Power Consumption 30 W",
    "product model": "VS24AH-P",
    "product name": "VS24AH-P Widescreen LCD Monitor",
    "product type": "LCD Monitor",
    "response time": "5 ms",
    "screen mode": "WUXGA",
    "standard refresh rate": "61 Hz",
    "standby power consumption": "500 mW",
    "technical information": "Screen Size 24.1\"",
    "upc": "886227438099",
    "vertical viewing angle": "178\u00c2\u00b0",
    "vesa mount compatible": "Yes",
    "vesa mount standard": "100 x 100",
    "video": "Brightness 300 Nit",
    "weight approximate": "10.14 lb",
    "width with stand": "22.11\""
}