{
    "<page title>": "Viewsonic 20 1\" VGA DVI 1600x1200 LCD Monitor VP201S VLCDS26064 4W w USB Hub 766907874624 | eBay",
    "aspect ratio": "4:3",
    "brightness": "250 cd/m\u00c2\u00b2",
    "condition": "Used: An item that has been used previously. The item may have some signs of cosmetic wear, but is fully\noperational and functions as intended. This item may be a floor model or store return that has been used. See the seller\u00e2\u0080\u0099s listing for full details and description of any imperfections.\nSee all condition definitions- opens in a new window or tab\n... Read moreabout the condition\nBrand:\nViewSonic",
    "contrast ratio": "400, 350",
    "display technology": "LCD",
    "model": "VP201s",
    "mpn": "MOLDVSVP201B, VP201SOB, VP201BH4PK, VIE2019, RBVP201B, VP201SS, VLCDS260642WVP201B, VP201B6PC, VP201BREF, DHVP201B, VP201B2HB1, VP201BHB1, VP201B2HB2, VP201BHB2, VP201S6PC, VP201B2HB3, VP201BHB3, VSVP201S, VP171BH3PK, eBay_ViewSonicVP201s20.1, 201BH, VP201S, DBVP201, VP201BOB, VP201SKIT, DHVP201S, VP201BH",
    "response time": "16 ms",
    "screen size": "20.1\"",
    "system": "Desktop",
    "upc": "766907874624",
    "video inputs": "DVI"
}