{
    "<page title>": "Acer V173DB 17\" LCD Monitor 1280 X 1024 Resolution  20000:1 Contrast Ratio Black | UK | Ebay Items | Best Deal Items | Auctions | Free Shipping | Goods | Services | Wholesales | Retail | Trade",
    "condition": "Item type:",
    "contrast ratio": "1000:1",
    "country": "Category",
    "display technology": "LCD",
    "item sort": "Sort order:",
    "max resolution": "1280 x 1024",
    "minimum bid count": "Maximum bid count:",
    "minimum price": "Maximum price:",
    "model": "V173DB",
    "payment method": "Show Items:",
    "screen size": "17\"",
    "video inputs": "VGA/SVGA D-Sub"
}