{
    "<page title>": "Nec Display Multisync Pa302w-bk-sv 29.8\" Gb-r Led Lcd Monitor - 16:10 - 6 Ms - Adjustable Display Angle - 2560 X 1600 - 1.07 Billion Colors - 340 Nit - 1,000:1 - Wqxga - Dvi - Hdmi - Displayport - Usb - 87 W - Black - Rohs - (PA302W-BK-SV) - SoftwareCity.ca - Canada",
    "adjustable display angle": "Yes",
    "adjustable display height": "Yes",
    "adjustable display pivot": "Yes",
    "aspect ratio": "16:10",
    "backlight technology": "GB-R LED",
    "brand name": "NEC Display",
    "brightness": "340 cd/m\u00c2\u00b2",
    "builtin devices": "USB Hub",
    "color": "Black",
    "color supported": "1.07 Billion Colors",
    "contrast ratio": "1,000:1",
    "depth": "3.2\" (82 mm)",
    "depth with stand": "11.9\" (301.6 mm)",
    "displayport": "Yes",
    "dvi": "Yes",
    "features": "DisplaySync Pro, Digital Uniformity Correction, Black eQualizer, Tiled Matrix, CableComp, AmbiBright, Eco Mode, Cable Management, Carbon Footprint Meter",
    "green compliance certificateauthority": "RoHS",
    "green compliant": "Yes",
    "hdcp supported": "Yes",
    "hdmi": "Yes",
    "height": "17.6\" (446.8 mm)",
    "height with stand": "24.3\" (616.4 mm)",
    "horizontal frequency": "98.70 kHz",
    "horizontal viewing angle": "178\u00c2\u00b0",
    "limited warranty": "4 Year",
    "manufacturer": "NEC Display Solutions",
    "manufacturer part number": "PA302W-BK-SV",
    "manufacturer website address": "http://www.necdisplay.com",
    "maximum resolution": "2560 x 1600",
    "mount type": "Arm-mountable",
    "number of screens": "1",
    "operating power consumption": "87 W",
    "package contents": "30\" Color Critical Desktop Monitor with SpectraViewII (Black) Power Cable DisplayPort Cable Mini DisplayPort to DisplayPort Cable DVI Cable USB Cable Mounting Screws SpectraView II USB drive (SVIISOFT) Color calibration sensor (MDSVSENSOR3)",
    "panel technology": "Advanced High Performance In-plane Switching (AH-IPS) Technology",
    "product line": "MultiSync",
    "product model": "PA302W-BK-SV",
    "product name": "30\" Color Critical Desktop Monitor with SpectraViewII (Black)",
    "product type": "LCD Monitor",
    "response time": "6 ms",
    "screen mode": "WQXGA",
    "screen size": "29.8\"",
    "standard refresh rate": "85 Hz",
    "standby power consumption": "1.40 W",
    "usb": "Yes",
    "vertical viewing angle": "178\u00c2\u00b0",
    "vesa mount compatible": "Yes",
    "vesa mount standard": "200 x 100",
    "weight approximate": "8.89 kg",
    "weight with stand approximate": "17.01 kg",
    "width": "27.1\" (688 mm)",
    "width with stand": "27.1\" (688.3 mm)"
}