{
    "<page title>": "Aoc E970swn 18.5\" Led Lcd Monitor - 16:9 - 5 Ms - Adjustable Display Angle - 1366 X 768 - 16.7 Million Colors - 200 Nit - 700:1 - Wxga - Vga - 15 W - Black - Rohs, Energy Star 6.0, Eup, Epeat Gold - (E970SWN) - SoftwareCity.ca - Canada",
    "adjustable display angle": "Yes",
    "adjustable display height": "No",
    "adjustable display pivot": "No",
    "aspect ratio": "16:9",
    "backlight technology": "LED",
    "brand name": "AOC",
    "brightness": "200 cd/m\u00c2\u00b2",
    "color": "Black",
    "color supported": "16.7 Million Colors",
    "contrast ratio": "700:1",
    "depth": "1.9\" (47.7 mm)",
    "depth with stand": "6.1\" (156 mm)",
    "displayport": "No",
    "dvi": "No",
    "features": "Eco Mode",
    "green compliance certificateauthority": "RoHS, ENERGY STAR 6.0, EuP, EPEAT Gold",
    "green compliant": "Yes",
    "hdmi": "No",
    "height": "10.7\" (271.6 mm)",
    "height with stand": "13.3\" (336.8 mm)",
    "horizontal frequency": "60 kHz",
    "horizontal viewing angle": "90\u00c2\u00b0",
    "limited warranty": "3 Year",
    "manufacturer": "AOC",
    "manufacturer part number": "E970SWN",
    "manufacturer website address": "http://us.aoc.com",
    "maximum resolution": "1366 x 768",
    "mount type": "Wall Mountable",
    "number of screens": "1",
    "offmode power consumption": "500 mW",
    "operating power consumption": "15 W",
    "platform supported": "PC",
    "product model": "E970SWN",
    "product name": "E970SWN Widescreen LCD Monitor",
    "product type": "LCD Monitor",
    "response time": "5 ms",
    "screen mode": "WXGA",
    "screen size": "18.5\"",
    "standard refresh rate": "60 Hz",
    "standby power consumption": "500 mW",
    "vertical viewing angle": "65\u00c2\u00b0",
    "vesa mount compatible": "Yes",
    "vesa mount standard": "100 x 100",
    "vga": "Yes",
    "weight approximate": "2.15 kg",
    "width": "17.2\" (437.4 mm)",
    "width with stand": "17.2\" (437.4 mm)"
}