{
    "<page title>": "Asus Vb198t-p 19\" Led Lcd Monitor - 4:3 - 5 Ms - Adjustable Display Angle - 1280 X 1024 - 16.7 Million Colors - 250 Nit - Sxga - Speakers - Dvi - Vga - 27 W - Black - Rohs, Tco Certified Displays 5.2, Energy Star, Erp, J-moss (japanese Rohs), Weee - (VB198T-P) - SoftwareCity.ca - Canada",
    "adjustable display angle": "Yes",
    "aspect ratio": "4:3",
    "backlight technology": "LED",
    "brand name": "Asus",
    "brightness": "250 cd/m\u00c2\u00b2",
    "builtin devices": "Speaker",
    "certifications  standards": "C-TickBSMICBCCCCEFCCGost-RISO-9241-307PSBTUV-ErgoTUV-GSUL/cULVCCIWHQL",
    "color": "Black",
    "color supported": "16.7 Million Colors",
    "contrast ratio": "50,000,000:1",
    "depth": "8.3\" (210 mm)",
    "dvi": "Yes",
    "features": "Splendid Video Intelligence Technology, Security Lock, Cable Management",
    "green compliance certificateauthority": "RoHS, TCO Certified Displays 5.2, ENERGY STAR, ErP, J-Moss (Japanese RoHS), WEEE",
    "green compliant": "Yes",
    "hdcp supported": "Yes",
    "height": "15.9\" (405 mm)",
    "horizontal frequency": "80 kHz",
    "horizontal viewing angle": "170\u00c2\u00b0",
    "limited warranty": "3 Year",
    "manufacturer": "ASUS Computer International",
    "manufacturer part number": "VB198T-P",
    "manufacturer website address": "http://www.asus.com",
    "maximum resolution": "1280 x 1024",
    "mount type": "Wall Mountable",
    "number of screens": "1",
    "number of speakers": "2",
    "offmode power consumption": "200 mW",
    "operating power consumption": "27 W",
    "package contents": "VB198T-P LCD MonitorDVI CableVGA CableAudio CableQuick Start GuideSupport CDWarranty Card",
    "platform supported": "PC",
    "product model": "VB198T-P",
    "product name": "VB198T-P LCD Monitor",
    "product series": "VB",
    "product type": "LCD Monitor",
    "response time": "5 ms",
    "screen mode": "SXGA",
    "screen size": "19\"",
    "speakers": "Yes",
    "standard refresh rate": "76 Hz",
    "standby power consumption": "300 mW",
    "vertical viewing angle": "160\u00c2\u00b0",
    "vesa mount compatible": "Yes",
    "vesa mount standard": "100 x 100",
    "vga": "Yes",
    "weight approximate": "3.20 kg",
    "width": "16.3\" (413 mm)"
}