{
    "<page title>": "ASUSPRO PB278Q 27\" Wide LED Black Multimedia Monitor (2560x1440/5ms/VGA/DVI-D/DisplayPort/HDMI) : Monitors : Monitors : Nexus Technology UK, Colchester, Essex",
    "aspect ratio": "16:9",
    "audio": "2 x 3W",
    "backlight": "LED",
    "brightness": "300 cd/m\u00c2\u00b2",
    "click image to enlarge": "\u00c2\u00a3442.34\n\u00c2\u00a3530.81 inc VAT\n3 Available\nAvailable for next day delivery if ordered before 5pm",
    "colours": "16.7 Million",
    "compliance": "TCO 5.2, UL/cUL, CB, CE, ErP, FCC, CCC, BSMI, Gost-R, C-Tick, VCCI, J-MOSS, RoHS, Windows 7 WHQL, HDMI, DP, PSE",
    "contrast ratio": "1000:1",
    "displayports": "1",
    "dvid ports": "1",
    "dynamic contrast ratio": "80, 000, 000:1",
    "ean": "4716659236511",
    "energy star": "5.0",
    "gross weight": "12Kg",
    "hdmi ports": "1",
    "headphone jacks": "1",
    "height adjustment": "120mm",
    "horizontal frequency range": "24kHz - 89kHz",
    "horizontal viewing angle": "178\u00c2\u00b0",
    "input power source": "Power Lead",
    "keywords": "Monitors, LED, IPS, PLS, 27\", 16:9, WQHD, 5ms, HDMI, Widescreen, Wall Mount",
    "line in jacks": "1",
    "manufacturer": "ASUS",
    "max resolution": "2560 x 1440",
    "model number": "PB278Q",
    "net weight": "8.8Kg",
    "normal power consumption": "60W",
    "package contents": "Monitor, DisplayPort cable, HDMI cable, Dual-link DVI cable, VGA cable, UK Power cord, Audio cable, Quick start guide",
    "package height": "22cm",
    "package length": "75cm",
    "package type": "Retail",
    "package width": "46.5cm",
    "pivot": "90\u00c2\u00b0",
    "pixel pitch": "0.233mm",
    "product code": "NEX-106964",
    "product group": "Monitors",
    "product height": "552mm",
    "product height without stand": "386.2mm",
    "product length": "218mm",
    "product length without stand": "69.6mm",
    "product name": "ASUSPRO PB278Q 27\" Wide LED Black Multimedia Monitor (2560x1440/5ms/VGA/DVI-D/DisplayPort/HDMI)",
    "product width": "643mm",
    "product width without stand": "643mm",
    "recommend resolution": "2560 x 1440",
    "response time": "5ms (GTG)",
    "royal mail compliance": "Not Compliant",
    "screen size": "27\"",
    "screen type": "PLS",
    "speakers": "Integrated",
    "special features": "mpeccable lifelike visuals with 27\u00c2\u0094 16:9 2560 x 1440 with 100% sRGB 178\u00c2\u00b0 wide-viewing angle, Ergonomic tilt, swivel, pivot, and height adjustment plus smart cable management",
    "standby power consumption": "0.5W",
    "swivel lr": "+60\u00c2\u00b0/-60\u00c2\u00b0",
    "tilt angle": "-5\u00c2\u00b0/20\u00c2\u00b0",
    "unit colour front": "Black",
    "unit colour rear": "Black",
    "unit colour stand": "Black",
    "upc": "886227236510",
    "vertical frequency range": "50Hz - 75Hz",
    "vertical viewing angle": "178\u00c2\u00b0",
    "vga ports": "1",
    "wall mount": "VESA 100mm x 100mm",
    "warranty direct with manufacturer": "3 Years On Site",
    "web address": "www.asus.com"
}