{
    "<page title>": "Cleverboxes - PLC1911S-B3 | Iiyama ProLite C1911S-3 (19 inch) LCD Monitor 1000:1 250cd/m2 1280x1024 5ms D-Sub/S-Video (Black)",
    "aspect ratio": "5:4",
    "audio line in ports": "1 x RCA",
    "audio line out ports": "1 x RCA",
    "backlight": "LED",
    "bnc port": "2 x BNC (In) \u2022 2 x BNC (Out)",
    "brightness": "250cd/m2",
    "case colour": "Black",
    "certifications": "CE, TUV/Bauart, CU",
    "contrast ratio": "1,000:1 (Static)",
    "dimensions": "40.7cm (W) x 20.05cm (D) x 43.15cm (H) - Weight 3.9kg",
    "display type": "LCD Display",
    "in the box": "Iiyama ProLite C1911S-3 LCD Monitor, power cable, D-Sub cable, BNC-RCA adaptor, stand, quick start guide, safety guide",
    "language selection": "8 Languages (EN, FR, DE, IT, ES, PT, NL, SE)",
    "operating systems supported": "Microsoft Windows 95, 98, Me, 2000, XP, Vista, 7",
    "pixel pitch": "0.294 x 0.294mm",
    "plug and play": "VESA DDC2B",
    "power adaptor type": "Internal",
    "power consumption": "19W (Max) /",
    "resolution native": "1280 x 1024 Pixels SXGA",
    "response time": "5ms",
    "scan frequency": "30 to 82KHz (Horizontal) x 56 to 75Hz (Vertical)",
    "screen dimensions": "19in Display Area - 37.63 x 30.1cm",
    "screen type": "TN LED-backlit 16.7 million Colour",
    "security locking mechanics": "Kensington Lock Compliant",
    "speakers": "2 x 1W",
    "svideo in": "1 x S-Video",
    "tilt forwardbackward": "up 20\u00b0",
    "user controls": "Picture (brightness, contrast, colour, tint, sharpness, colour temperature), sound (bass, treble, balance, volume, audio source), option (OSD language, OSD timeout, AV switch, auto off, no signal off, reset), PC (auto adjust, H. position, V. position, clock, phase) and 5 Front controls (Power, Input Select/ Select, Scroll up, Scroll down, Meu/ Exit)",
    "vga in": "1 x 15-pin D-Sub",
    "view angle": "170\u00b0 (Horizontal - Max) x 160\u00b0 (Vertical - Max)",
    "voltagefrequency": "100 to 240VAC / 50 to 60Hz",
    "wall mount": "Yes , VESA Compliant",
    "warranty": "2 years on-site."
}