{
    "<page title>": "Cleverboxes - BDL:K1428V140-UK | Fujitsu P Series Premium P24W-6 (24 inch) IPS LED Display 1000:1 300cd/m2 1920x1200 5ms DisplayPort (UK)",
    "antiglare  antistatic": "Anti-Glare \u2022 Hard Coating 3H",
    "aspect ratio": "16:10",
    "backlight": "LED",
    "barcode": "4051554318796",
    "brightness": "300cd/m2",
    "case colour": "Marble Grey",
    "certifications": "EN 60950, CE certification according to EC Directive 2004/108/EEC, RoHS, WEEE, IT-Eco-Declaration",
    "contrast ratio": "1,000:1 (Static) , 20,000,000:1 (Dynamic)",
    "description": "Optimized and relaxed position - with ergonomic stand featuring height adjust, swivel, tilt and 90\u00b0 rotation. Highly flexible connectivity through different interfaces - 4 x USB, DisplayPort, HDCP (via DVI-D), DVI and Analog. The abundant screen size of 61 cm (24-inch) provides the professional 16:10 format with 1920 x 1200 pixels for view of 2 x DIN A4 pages side by side. Representative design with space saving front frame and discretely integrated speakers. With DisplayView Manageability tools ready for remote inventory gathering and configuration tasks.",
    "digital in": "1 x DVI (with HDCP)",
    "dimensions": "55.9cm (W) x 19.7cm (D) x 39.5cm (H) - Weight 6.7kg",
    "displayport in": "1 x DisplayPort",
    "environmental": "Operating Temperature 5 to 35\u00b0C",
    "headphone ports": "1 x 3.5mm Stereo Mini Jack",
    "height adjustable": "Yes",
    "language selection": "Arabic, Czech, Danish, Dutch, English, Finnish, French, German, Italian, Norwegian, Polish, Portuguese, Russian, Spanish, Swedish, Turkish",
    "lifetime": "70,000 hours",
    "model name": "P24W-6",
    "pivot": "Yes",
    "pixel pitch": "0.270mm",
    "plug and play": "VESA DDC/ CI",
    "power adaptor type": "Integrated",
    "power consumption": "36W (Max)",
    "product family": "P Series Premium",
    "product type": "Display",
    "resolution native": "1920 x 1200 Pixels",
    "response time": "5ms",
    "scan frequency horizontal": "30KHz to 82KHz (Digital)",
    "scan frequency vertical": "56Hz to 76Hz (Digital)",
    "screen dimensions": "24in Display Area - 51.8 x 32.4cm",
    "screen type": "In Plane Switching (IPS) 16.7 Million Colour",
    "security locking mechanics": "Kensington Lock Slot",
    "speakers": "2 x 1.5W",
    "swivel": "340\u00b0",
    "tilt forwardbackward": "-5 to +35\u00b0",
    "usb ports": "4 x USB 2.0 (Downstream) \u2022 1 x USB (Upstream)",
    "user controls": "Mute \u2022 Volume",
    "vga in": "1 x 15-pin D-sub",
    "view angle": "178\u00b0 (Horizontal - Max) x 178\u00b0 (Vertical - Max)",
    "voltagefrequency": "100 to 240VAC / 50 to 60Hz",
    "wall mount": "Yes , VESA Compliant - 100mm x 100mm",
    "warranty": "3 Years Collect and Return"
}